{"head": {"link": [], "vars": ["p1", "entities"]}, "results": {"distinct": false, "ordered": true, "bindings": [{"p1": {"type": "uri", "value": "http://www.wikidata.org/prop/direct/P1071"}, "entities": {"type": "typed-literal", "datatype": "http://www.w3.org/2001/XMLSchema#integer", "value": "75746"}}, {"p1": {"type": "uri", "value": "http://www.wikidata.org/prop/direct/P9122"}, "entities": {"type": "typed-literal", "datatype": "http://www.w3.org/2001/XMLSchema#integer", "value": "259"}}, {"p1": {"type": "uri", "value": "http://www.wikidata.org/prop/direct/P9172"}, "entities": {"type": "typed-literal", "datatype": "http://www.w3.org/2001/XMLSchema#integer", "value": "101"}}, {"p1": {"type": "uri", "value": "http://www.wikidata.org/prop/direct/P1168"}, "entities": {"type": "typed-literal", "datatype": "http://www.w3.org/2001/XMLSchema#integer", "value": "345"}}, {"p1": {"type": "uri", "value": "http://www.wikidata.org/prop/direct/P1064"}, "entities": {"type": "typed-literal", "datatype": "http://www.w3.org/2001/XMLSchema#integer", "value": "23138"}}, {"p1": {"type": "uri", "value": "http://www.wikidata.org/prop/direct/P9183"}, "entities": {"type": "typed-literal", "datatype": "http://www.w3.org/2001/XMLSchema#integer", "value": "4147"}}, {"p1": {"type": "uri", "value": "http://www.wikidata.org/prop/direct/P8729"}, "entities": {"type": "typed-literal", "datatype": "http://www.w3.org/2001/XMLSchema#integer", "value": "1746"}}, {"p1": {"type": "uri", "value": "http://www.wikidata.org/prop/direct/P1059"}, "entities": {"type": "typed-literal", "datatype": "http://www.w3.org/2001/XMLSchema#integer", "value": "3319"}}, {"p1": {"type": "uri", "value": "http://www.wikidata.org/prop/direct/P121"}, "entities": {"type": "typed-literal", "datatype": "http://www.w3.org/2001/XMLSchema#integer", "value": "10450"}}, {"p1": {"type": "uri", "value": "http://www.wikidata.org/prop/direct/P1067"}, "entities": {"type": "typed-literal", "datatype": "http://www.w3.org/2001/XMLSchema#integer", "value": "8605"}}, {"p1": {"type": "uri", "value": "http://www.wikidata.org/prop/direct/P8780"}, "entities": {"type": "typed-literal", "datatype": "http://www.w3.org/2001/XMLSchema#integer", "value": "48"}}, {"p1": {"type": "uri", "value": "http://www.wikidata.org/prop/direct/P8809"}, "entities": {"type": "typed-literal", "datatype": "http://www.w3.org/2001/XMLSchema#integer", "value": "31"}}, {"p1": {"type": "uri", "value": "http://www.wikidata.org/prop/direct/P8721"}, "entities": {"type": "typed-literal", "datatype": "http://www.w3.org/2001/XMLSchema#integer", "value": "314"}}, {"p1": {"type": "uri", "value": "http://www.wikidata.org/prop/direct/P878"}, "entities": {"type": "typed-literal", "datatype": "http://www.w3.org/2001/XMLSchema#integer", "value": "180"}}, {"p1": {"type": "uri", "value": "http://www.wikidata.org/prop/direct/P9430"}, "entities": {"type": "typed-literal", "datatype": "http://www.w3.org/2001/XMLSchema#integer", "value": "1057"}}, {"p1": {"type": "uri", "value": "http://www.wikidata.org/prop/direct/P9316"}, "entities": {"type": "typed-literal", "datatype": "http://www.w3.org/2001/XMLSchema#integer", "value": "171"}}, {"p1": {"type": "uri", "value": "http://www.wikidata.org/prop/direct/P9469"}, "entities": {"type": "typed-literal", "datatype": "http://www.w3.org/2001/XMLSchema#integer", "value": "111"}}, {"p1": {"type": "uri", "value": "http://www.wikidata.org/prop/direct/P1444"}, "entities": {"type": "typed-literal", "datatype": "http://www.w3.org/2001/XMLSchema#integer", "value": "29274"}}, {"p1": {"type": "uri", "value": "http://www.wikidata.org/prop/direct/P1274"}, "entities": {"type": "typed-literal", "datatype": "http://www.w3.org/2001/XMLSchema#integer", "value": "19089"}}, {"p1": {"type": "uri", "value": "http://www.wikidata.org/prop/direct/P1409"}, "entities": {"type": "typed-literal", "datatype": "http://www.w3.org/2001/XMLSchema#integer", "value": "20869"}}, {"p1": {"type": "uri", "value": "http://www.wikidata.org/prop/direct/P9289"}, "entities": {"type": "typed-literal", "datatype": "http://www.w3.org/2001/XMLSchema#integer", "value": "1149"}}, {"p1": {"type": "uri", "value": "http://www.wikidata.org/prop/direct/P9391"}, "entities": {"type": "typed-literal", "datatype": "http://www.w3.org/2001/XMLSchema#integer", "value": "1089"}}, {"p1": {"type": "uri", "value": "http://www.wikidata.org/prop/direct/P1302"}, "entities": {"type": "typed-literal", "datatype": "http://www.w3.org/2001/XMLSchema#integer", "value": "3570"}}, {"p1": {"type": "uri", "value": "http://www.wikidata.org/prop/direct/P1212"}, "entities": {"type": "typed-literal", "datatype": "http://www.w3.org/2001/XMLSchema#integer", "value": "6009"}}, {"p1": {"type": "uri", "value": "http://www.wikidata.org/prop/direct/P882"}, "entities": {"type": "typed-literal", "datatype": "http://www.w3.org/2001/XMLSchema#integer", "value": "3296"}}, {"p1": {"type": "uri", "value": "http://www.wikidata.org/prop/direct/P9033"}, "entities": {"type": "typed-literal", "datatype": "http://www.w3.org/2001/XMLSchema#integer", "value": "4544"}}, {"p1": {"type": "uri", "value": "http://www.wikidata.org/prop/direct/P1377"}, "entities": {"type": "typed-literal", "datatype": "http://www.w3.org/2001/XMLSchema#integer", "value": "178"}}, {"p1": {"type": "uri", "value": "http://www.wikidata.org/prop/direct/P1257"}, "entities": {"type": "typed-literal", "datatype": "http://www.w3.org/2001/XMLSchema#integer", "value": "11271"}}, {"p1": {"type": "uri", "value": "http://www.wikidata.org/prop/direct/P9054"}, "entities": {"type": "typed-literal", "datatype": "http://www.w3.org/2001/XMLSchema#integer", "value": "645"}}, {"p1": {"type": "uri", "value": "http://www.wikidata.org/prop/direct/P1047"}, "entities": {"type": "typed-literal", "datatype": "http://www.w3.org/2001/XMLSchema#integer", "value": "42963"}}, {"p1": {"type": "uri", "value": "http://www.wikidata.org/prop/direct/P8817"}, "entities": {"type": "typed-literal", "datatype": "http://www.w3.org/2001/XMLSchema#integer", "value": "1320"}}, {"p1": {"type": "uri", "value": "http://www.wikidata.org/prop/direct/P9082"}, "entities": {"type": "typed-literal", "datatype": "http://www.w3.org/2001/XMLSchema#integer", "value": "72"}}, {"p1": {"type": "uri", "value": "http://www.wikidata.org/prop/direct/P8861"}, "entities": {"type": "typed-literal", "datatype": "http://www.w3.org/2001/XMLSchema#integer", "value": "1056"}}, {"p1": {"type": "uri", "value": "http://www.wikidata.org/prop/direct/P9625"}, "entities": {"type": "typed-literal", "datatype": "http://www.w3.org/2001/XMLSchema#integer", "value": "1176"}}, {"p1": {"type": "uri", "value": "http://www.wikidata.org/prop/direct/P8683"}, "entities": {"type": "typed-literal", "datatype": "http://www.w3.org/2001/XMLSchema#integer", "value": "255"}}, {"p1": {"type": "uri", "value": "http://www.wikidata.org/prop/direct/P9640"}, "entities": {"type": "typed-literal", "datatype": "http://www.w3.org/2001/XMLSchema#integer", "value": "343"}}, {"p1": {"type": "uri", "value": "http://www.wikidata.org/prop/direct/P8720"}, "entities": {"type": "typed-literal", "datatype": "http://www.w3.org/2001/XMLSchema#integer", "value": "766"}}, {"p1": {"type": "uri", "value": "http://www.wikidata.org/prop/direct/P952"}, "entities": {"type": "typed-literal", "datatype": "http://www.w3.org/2001/XMLSchema#integer", "value": "269"}}, {"p1": {"type": "uri", "value": "http://www.wikidata.org/prop/direct/P1029"}, "entities": {"type": "typed-literal", "datatype": "http://www.w3.org/2001/XMLSchema#integer", "value": "1995"}}, {"p1": {"type": "uri", "value": "http://www.wikidata.org/prop/direct/P1431"}, "entities": {"type": "typed-literal", "datatype": "http://www.w3.org/2001/XMLSchema#integer", "value": "9869"}}, {"p1": {"type": "uri", "value": "http://www.wikidata.org/prop/direct/P1418"}, "entities": {"type": "typed-literal", "datatype": "http://www.w3.org/2001/XMLSchema#integer", "value": "313"}}, {"p1": {"type": "uri", "value": "http://www.wikidata.org/prop/direct/P9501"}, "entities": {"type": "typed-literal", "datatype": "http://www.w3.org/2001/XMLSchema#integer", "value": "2434"}}, {"p1": {"type": "uri", "value": "http://www.wikidata.org/prop/direct/P9654"}, "entities": {"type": "typed-literal", "datatype": "http://www.w3.org/2001/XMLSchema#integer", "value": "3435"}}, {"p1": {"type": "uri", "value": "http://www.wikidata.org/prop/direct/P9541"}, "entities": {"type": "typed-literal", "datatype": "http://www.w3.org/2001/XMLSchema#integer", "value": "531"}}, {"p1": {"type": "uri", "value": "http://www.wikidata.org/prop/direct/P1420"}, "entities": {"type": "typed-literal", "datatype": "http://www.w3.org/2001/XMLSchema#integer", "value": "26792"}}, {"p1": {"type": "uri", "value": "http://www.wikidata.org/prop/direct/P9110"}, "entities": {"type": "typed-literal", "datatype": "http://www.w3.org/2001/XMLSchema#integer", "value": "296"}}, {"p1": {"type": "uri", "value": "http://www.wikidata.org/prop/direct/P9214"}, "entities": {"type": "typed-literal", "datatype": "http://www.w3.org/2001/XMLSchema#integer", "value": "339"}}, {"p1": {"type": "uri", "value": "http://www.wikidata.org/prop/direct/P1427"}, "entities": {"type": "typed-literal", "datatype": "http://www.w3.org/2001/XMLSchema#integer", "value": "35866"}}, {"p1": {"type": "uri", "value": "http://www.wikidata.org/prop/direct/P1410"}, "entities": {"type": "typed-literal", "datatype": "http://www.w3.org/2001/XMLSchema#integer", "value": "8432"}}, {"p1": {"type": "uri", "value": "http://www.wikidata.org/prop/direct/P917"}, "entities": {"type": "typed-literal", "datatype": "http://www.w3.org/2001/XMLSchema#integer", "value": "128"}}]}}