{"head": {"link": [], "vars": ["p1", "entities"]}, "results": {"distinct": false, "ordered": true, "bindings": [{"p1": {"type": "uri", "value": "http://www.wikidata.org/prop/direct/P5762"}, "entities": {"type": "typed-literal", "datatype": "http://www.w3.org/2001/XMLSchema#integer", "value": "3"}}, {"p1": {"type": "uri", "value": "http://www.wikidata.org/prop/direct/P1099"}, "entities": {"type": "typed-literal", "datatype": "http://www.w3.org/2001/XMLSchema#integer", "value": "49"}}, {"p1": {"type": "uri", "value": "http://www.wikidata.org/prop/direct/P5942"}, "entities": {"type": "typed-literal", "datatype": "http://www.w3.org/2001/XMLSchema#integer", "value": "194"}}, {"p1": {"type": "uri", "value": "http://www.wikidata.org/prop/direct/P6143"}, "entities": {"type": "typed-literal", "datatype": "http://www.w3.org/2001/XMLSchema#integer", "value": "207"}}, {"p1": {"type": "uri", "value": "http://www.wikidata.org/prop/direct/P6215"}, "entities": {"type": "typed-literal", "datatype": "http://www.w3.org/2001/XMLSchema#integer", "value": "123"}}, {"p1": {"type": "uri", "value": "http://www.wikidata.org/prop/direct/P7520"}, "entities": {"type": "typed-literal", "datatype": "http://www.w3.org/2001/XMLSchema#integer", "value": "89"}}, {"p1": {"type": "uri", "value": "http://www.wikidata.org/prop/direct/P8053"}, "entities": {"type": "typed-literal", "datatype": "http://www.w3.org/2001/XMLSchema#integer", "value": "1718"}}, {"p1": {"type": "uri", "value": "http://www.wikidata.org/prop/direct/P5823"}, "entities": {"type": "typed-literal", "datatype": "http://www.w3.org/2001/XMLSchema#integer", "value": "4234"}}, {"p1": {"type": "uri", "value": "http://www.wikidata.org/prop/direct/P8664"}, "entities": {"type": "typed-literal", "datatype": "http://www.w3.org/2001/XMLSchema#integer", "value": "116"}}, {"p1": {"type": "uri", "value": "http://www.wikidata.org/prop/direct/P8177"}, "entities": {"type": "typed-literal", "datatype": "http://www.w3.org/2001/XMLSchema#integer", "value": "274"}}, {"p1": {"type": "uri", "value": "http://www.wikidata.org/prop/direct/P6489"}, "entities": {"type": "typed-literal", "datatype": "http://www.w3.org/2001/XMLSchema#integer", "value": "131"}}, {"p1": {"type": "uri", "value": "http://www.wikidata.org/prop/direct/P7783"}, "entities": {"type": "typed-literal", "datatype": "http://www.w3.org/2001/XMLSchema#integer", "value": "1260"}}, {"p1": {"type": "uri", "value": "http://www.wikidata.org/prop/direct/P5965"}, "entities": {"type": "typed-literal", "datatype": "http://www.w3.org/2001/XMLSchema#integer", "value": "14388"}}, {"p1": {"type": "uri", "value": "http://www.wikidata.org/prop/direct/P6377"}, "entities": {"type": "typed-literal", "datatype": "http://www.w3.org/2001/XMLSchema#integer", "value": "34"}}, {"p1": {"type": "uri", "value": "http://www.wikidata.org/prop/direct/P6686"}, "entities": {"type": "typed-literal", "datatype": "http://www.w3.org/2001/XMLSchema#integer", "value": "17"}}, {"p1": {"type": "uri", "value": "http://www.wikidata.org/prop/direct/P3914"}, "entities": {"type": "typed-literal", "datatype": "http://www.w3.org/2001/XMLSchema#integer", "value": "649"}}, {"p1": {"type": "uri", "value": "http://www.wikidata.org/prop/direct/P4253"}, "entities": {"type": "typed-literal", "datatype": "http://www.w3.org/2001/XMLSchema#integer", "value": "765"}}, {"p1": {"type": "uri", "value": "http://www.wikidata.org/prop/direct/P2667"}, "entities": {"type": "typed-literal", "datatype": "http://www.w3.org/2001/XMLSchema#integer", "value": "1524"}}, {"p1": {"type": "uri", "value": "http://www.wikidata.org/prop/direct/P2217"}, "entities": {"type": "typed-literal", "datatype": "http://www.w3.org/2001/XMLSchema#integer", "value": "66"}}, {"p1": {"type": "uri", "value": "http://www.wikidata.org/prop/direct/P7164"}, "entities": {"type": "typed-literal", "datatype": "http://www.w3.org/2001/XMLSchema#integer", "value": "51"}}, {"p1": {"type": "uri", "value": "http://www.wikidata.org/prop/direct/P6280"}, "entities": {"type": "typed-literal", "datatype": "http://www.w3.org/2001/XMLSchema#integer", "value": "722"}}, {"p1": {"type": "uri", "value": "http://www.wikidata.org/prop/direct/P8493"}, "entities": {"type": "typed-literal", "datatype": "http://www.w3.org/2001/XMLSchema#integer", "value": "59"}}, {"p1": {"type": "uri", "value": "http://www.wikidata.org/prop/direct/P5029"}, "entities": {"type": "typed-literal", "datatype": "http://www.w3.org/2001/XMLSchema#integer", "value": "1100"}}, {"p1": {"type": "uri", "value": "http://www.wikidata.org/prop/direct/P7587"}, "entities": {"type": "typed-literal", "datatype": "http://www.w3.org/2001/XMLSchema#integer", "value": "34"}}, {"p1": {"type": "uri", "value": "http://www.wikidata.org/prop/direct/P6326"}, "entities": {"type": "typed-literal", "datatype": "http://www.w3.org/2001/XMLSchema#integer", "value": "31"}}, {"p1": {"type": "uri", "value": "http://www.wikidata.org/prop/direct/P3419"}, "entities": {"type": "typed-literal", "datatype": "http://www.w3.org/2001/XMLSchema#integer", "value": "486"}}, {"p1": {"type": "uri", "value": "http://www.wikidata.org/prop/direct/P4006"}, "entities": {"type": "typed-literal", "datatype": "http://www.w3.org/2001/XMLSchema#integer", "value": "18"}}, {"p1": {"type": "uri", "value": "http://www.wikidata.org/prop/direct/P1887"}, "entities": {"type": "typed-literal", "datatype": "http://www.w3.org/2001/XMLSchema#integer", "value": "80"}}, {"p1": {"type": "uri", "value": "http://www.wikidata.org/prop/direct/P3155"}, "entities": {"type": "typed-literal", "datatype": "http://www.w3.org/2001/XMLSchema#integer", "value": "5265"}}, {"p1": {"type": "uri", "value": "http://www.wikidata.org/prop/direct/P6408"}, "entities": {"type": "typed-literal", "datatype": "http://www.w3.org/2001/XMLSchema#integer", "value": "2303"}}, {"p1": {"type": "uri", "value": "http://www.wikidata.org/prop/direct/P5073"}, "entities": {"type": "typed-literal", "datatype": "http://www.w3.org/2001/XMLSchema#integer", "value": "126"}}, {"p1": {"type": "uri", "value": "http://www.wikidata.org/prop/direct/P3754"}, "entities": {"type": "typed-literal", "datatype": "http://www.w3.org/2001/XMLSchema#integer", "value": "32"}}, {"p1": {"type": "uri", "value": "http://www.wikidata.org/prop/direct/P4700"}, "entities": {"type": "typed-literal", "datatype": "http://www.w3.org/2001/XMLSchema#integer", "value": "333"}}, {"p1": {"type": "uri", "value": "http://www.wikidata.org/prop/direct/P4706"}, "entities": {"type": "typed-literal", "datatype": "http://www.w3.org/2001/XMLSchema#integer", "value": "312"}}, {"p1": {"type": "uri", "value": "http://www.wikidata.org/prop/direct/P5283"}, "entities": {"type": "typed-literal", "datatype": "http://www.w3.org/2001/XMLSchema#integer", "value": "87"}}, {"p1": {"type": "uri", "value": "http://www.wikidata.org/prop/direct/P5196"}, "entities": {"type": "typed-literal", "datatype": "http://www.w3.org/2001/XMLSchema#integer", "value": "153"}}, {"p1": {"type": "uri", "value": "http://www.wikidata.org/prop/direct/P5688"}, "entities": {"type": "typed-literal", "datatype": "http://www.w3.org/2001/XMLSchema#integer", "value": "395"}}, {"p1": {"type": "uri", "value": "http://www.wikidata.org/prop/direct/P5215"}, "entities": {"type": "typed-literal", "datatype": "http://www.w3.org/2001/XMLSchema#integer", "value": "2"}}, {"p1": {"type": "uri", "value": "http://www.wikidata.org/prop/direct/P4322"}, "entities": {"type": "typed-literal", "datatype": "http://www.w3.org/2001/XMLSchema#integer", "value": "1137"}}, {"p1": {"type": "uri", "value": "http://www.wikidata.org/prop/direct/P5727"}, "entities": {"type": "typed-literal", "datatype": "http://www.w3.org/2001/XMLSchema#integer", "value": "3"}}, {"p1": {"type": "uri", "value": "http://www.wikidata.org/prop/direct/P4510"}, "entities": {"type": "typed-literal", "datatype": "http://www.w3.org/2001/XMLSchema#integer", "value": "61271"}}, {"p1": {"type": "uri", "value": "http://www.wikidata.org/prop/direct/P514"}, "entities": {"type": "typed-literal", "datatype": "http://www.w3.org/2001/XMLSchema#integer", "value": "24"}}, {"p1": {"type": "uri", "value": "http://www.wikidata.org/prop/direct/P8634"}, "entities": {"type": "typed-literal", "datatype": "http://www.w3.org/2001/XMLSchema#integer", "value": "117"}}, {"p1": {"type": "uri", "value": "http://www.wikidata.org/prop/direct/P5603"}, "entities": {"type": "typed-literal", "datatype": "http://www.w3.org/2001/XMLSchema#integer", "value": "731"}}, {"p1": {"type": "uri", "value": "http://www.wikidata.org/prop/direct/P4880"}, "entities": {"type": "typed-literal", "datatype": "http://www.w3.org/2001/XMLSchema#integer", "value": "30"}}, {"p1": {"type": "uri", "value": "http://www.wikidata.org/prop/direct/P5262"}, "entities": {"type": "typed-literal", "datatype": "http://www.w3.org/2001/XMLSchema#integer", "value": "16"}}, {"p1": {"type": "uri", "value": "http://www.wikidata.org/prop/direct/P1594"}, "entities": {"type": "typed-literal", "datatype": "http://www.w3.org/2001/XMLSchema#integer", "value": "2644"}}, {"p1": {"type": "uri", "value": "http://www.wikidata.org/prop/direct/P6064"}, "entities": {"type": "typed-literal", "datatype": "http://www.w3.org/2001/XMLSchema#integer", "value": "12"}}, {"p1": {"type": "uri", "value": "http://www.wikidata.org/prop/direct/P5423"}, "entities": {"type": "typed-literal", "datatype": "http://www.w3.org/2001/XMLSchema#integer", "value": "21"}}, {"p1": {"type": "uri", "value": "http://www.wikidata.org/prop/direct/P1011"}, "entities": {"type": "typed-literal", "datatype": "http://www.w3.org/2001/XMLSchema#integer", "value": "8"}}]}}