{"head": {"link": [], "vars": ["p1", "p2"]}, "results": {"distinct": false, "ordered": true, "bindings": [{"p1": {"type": "uri", "value": "http://wikidata.dbpedia.org/property/colourname"}, "p2": {"type": "uri", "value": "http://www.w3.org/1999/02/22-rdf-syntax-ns#type"}}, {"p1": {"type": "uri", "value": "http://wikidata.dbpedia.org/property/colourname"}, "p2": {"type": "uri", "value": "http://www.w3.org/2000/01/rdf-schema#label"}}, {"p1": {"type": "uri", "value": "http://wikidata.dbpedia.org/property/colourname"}, "p2": {"type": "uri", "value": "http://www.w3.org/2000/01/rdf-schema#comment"}}, {"p1": {"type": "uri", "value": "http://wikidata.dbpedia.org/property/colourname"}, "p2": {"type": "uri", "value": "http://purl.org/dc/terms/subject"}}, {"p1": {"type": "uri", "value": "http://wikidata.dbpedia.org/property/colourname"}, "p2": {"type": "uri", "value": "http://dbpedia.org/ontology/wikiPageExternalLink"}}, {"p1": {"type": "uri", "value": "http://wikidata.dbpedia.org/property/colourname"}, "p2": {"type": "uri", "value": "http://wikidata.dbpedia.org/property/commons"}}, {"p1": {"type": "uri", "value": "http://wikidata.dbpedia.org/property/colourname"}, "p2": {"type": "uri", "value": "http://wikidata.dbpedia.org/property/colortexto"}}, {"p1": {"type": "uri", "value": "http://wikidata.dbpedia.org/property/colourname"}, "p2": {"type": "uri", "value": "http://wikidata.dbpedia.org/property/auteur"}}, {"p1": {"type": "uri", "value": "http://wikidata.dbpedia.org/property/colourname"}, "p2": {"type": "uri", "value": "http://wikidata.dbpedia.org/property/frequ\u00eancia"}}, {"p1": {"type": "uri", "value": "http://wikidata.dbpedia.org/property/colourname"}, "p2": {"type": "uri", "value": "http://wikidata.dbpedia.org/property/corTexto"}}, {"p1": {"type": "uri", "value": "http://wikidata.dbpedia.org/property/colourname"}, "p2": {"type": "uri", "value": "http://dbpedia.org/ontology/thumbnail"}}, {"p1": {"type": "uri", "value": "http://wikidata.dbpedia.org/property/colourname"}, "p2": {"type": "uri", "value": "http://xmlns.com/foaf/0.1/depiction"}}, {"p1": {"type": "uri", "value": "http://wikidata.dbpedia.org/property/colourname"}, "p2": {"type": "uri", "value": "http://wikidata.dbpedia.org/property/wiktionary"}}, {"p1": {"type": "uri", "value": "http://wikidata.dbpedia.org/property/colourname"}, "p2": {"type": "uri", "value": "http://wikidata.dbpedia.org/property/ann\u00e9e"}}, {"p1": {"type": "uri", "value": "http://wikidata.dbpedia.org/property/colourname"}, "p2": {"type": "uri", "value": "http://wikidata.dbpedia.org/property/lieu"}}, {"p1": {"type": "uri", "value": "http://wikidata.dbpedia.org/property/colourname"}, "p2": {"type": "uri", "value": "http://wikidata.dbpedia.org/ontology/thumbnail"}}, {"p1": {"type": "uri", "value": "http://wikidata.dbpedia.org/property/colourname"}, "p2": {"type": "uri", "value": "http://wikidata.dbpedia.org/property/b"}}, {"p1": {"type": "uri", "value": "http://wikidata.dbpedia.org/property/colourname"}, "p2": {"type": "uri", "value": "http://wikidata.dbpedia.org/property/c"}}, {"p1": {"type": "uri", "value": "http://wikidata.dbpedia.org/property/colourname"}, "p2": {"type": "uri", "value": "http://wikidata.dbpedia.org/property/commonscat"}}, {"p1": {"type": "uri", "value": "http://wikidata.dbpedia.org/property/colourname"}, "p2": {"type": "uri", "value": "http://wikidata.dbpedia.org/property/d"}}, {"p1": {"type": "uri", "value": "http://wikidata.dbpedia.org/property/colourname"}, "p2": {"type": "uri", "value": "http://wikidata.dbpedia.org/property/datum"}}, {"p1": {"type": "uri", "value": "http://wikidata.dbpedia.org/property/colourname"}, "p2": {"type": "uri", "value": "http://wikidata.dbpedia.org/property/float"}}, {"p1": {"type": "uri", "value": "http://wikidata.dbpedia.org/property/colourname"}, "p2": {"type": "uri", "value": "http://wikidata.dbpedia.org/property/g"}}, {"p1": {"type": "uri", "value": "http://wikidata.dbpedia.org/property/colourname"}, "p2": {"type": "uri", "value": "http://wikidata.dbpedia.org/property/hex"}}, {"p1": {"type": "uri", "value": "http://wikidata.dbpedia.org/property/colourname"}, "p2": {"type": "uri", "value": "http://wikidata.dbpedia.org/property/hrsg"}}, {"p1": {"type": "uri", "value": "http://wikidata.dbpedia.org/property/colourname"}, "p2": {"type": "uri", "value": "http://wikidata.dbpedia.org/property/imagen"}}, {"p1": {"type": "uri", "value": "http://wikidata.dbpedia.org/property/colourname"}, "p2": {"type": "uri", "value": "http://wikidata.dbpedia.org/property/issn"}}, {"p1": {"type": "uri", "value": "http://wikidata.dbpedia.org/property/colourname"}, "p2": {"type": "uri", "value": "http://wikidata.dbpedia.org/property/lang"}}, {"p1": {"type": "uri", "value": "http://wikidata.dbpedia.org/property/colourname"}, "p2": {"type": "uri", "value": "http://wikidata.dbpedia.org/property/name"}}, {"p1": {"type": "uri", "value": "http://wikidata.dbpedia.org/property/colourname"}, "p2": {"type": "uri", "value": "http://wikidata.dbpedia.org/property/nummer"}}, {"p1": {"type": "uri", "value": "http://wikidata.dbpedia.org/property/colourname"}, "p2": {"type": "uri", "value": "http://wikidata.dbpedia.org/property/ort"}}, {"p1": {"type": "uri", "value": "http://wikidata.dbpedia.org/property/colourname"}, "p2": {"type": "uri", "value": "http://wikidata.dbpedia.org/property/s"}}, {"p1": {"type": "uri", "value": "http://wikidata.dbpedia.org/property/colourname"}, "p2": {"type": "uri", "value": "http://wikidata.dbpedia.org/property/source"}}, {"p1": {"type": "uri", "value": "http://wikidata.dbpedia.org/property/colourname"}, "p2": {"type": "uri", "value": "http://wikidata.dbpedia.org/property/text"}}, {"p1": {"type": "uri", "value": "http://wikidata.dbpedia.org/property/colourname"}, "p2": {"type": "uri", "value": "http://wikidata.dbpedia.org/property/titel"}}, {"p1": {"type": "uri", "value": "http://wikidata.dbpedia.org/property/colourname"}, "p2": {"type": "uri", "value": "http://wikidata.dbpedia.org/property/title"}}, {"p1": {"type": "uri", "value": "http://wikidata.dbpedia.org/property/colourname"}, "p2": {"type": "uri", "value": "http://wikidata.dbpedia.org/property/typ"}}, {"p1": {"type": "uri", "value": "http://wikidata.dbpedia.org/property/colourname"}, "p2": {"type": "uri", "value": "http://wikidata.dbpedia.org/property/url"}}, {"p1": {"type": "uri", "value": "http://wikidata.dbpedia.org/property/colourname"}, "p2": {"type": "uri", "value": "http://wikidata.dbpedia.org/property/v"}}, {"p1": {"type": "uri", "value": "http://wikidata.dbpedia.org/property/colourname"}, "p2": {"type": "uri", "value": "http://wikidata.dbpedia.org/property/wayback"}}, {"p1": {"type": "uri", "value": "http://wikidata.dbpedia.org/property/colourname"}, "p2": {"type": "uri", "value": "http://wikidata.dbpedia.org/property/y"}}, {"p1": {"type": "uri", "value": "http://wikidata.dbpedia.org/property/colourname"}, "p2": {"type": "uri", "value": "http://wikidata.dbpedia.org/property/collection"}}, {"p1": {"type": "uri", "value": "http://wikidata.dbpedia.org/property/colourname"}, "p2": {"type": "uri", "value": "http://wikidata.dbpedia.org/property/wikiquote"}}, {"p1": {"type": "uri", "value": "http://wikidata.dbpedia.org/property/colourname"}, "p2": {"type": "uri", "value": "http://wikidata.dbpedia.org/property/passage"}}, {"p1": {"type": "uri", "value": "http://wikidata.dbpedia.org/property/colourname"}, "p2": {"type": "uri", "value": "http://wikidata.dbpedia.org/property/tome"}}, {"p1": {"type": "uri", "value": "http://wikidata.dbpedia.org/property/colourname"}, "p2": {"type": "uri", "value": "http://wikidata.dbpedia.org/property/traducteur"}}, {"p1": {"type": "uri", "value": "http://wikidata.dbpedia.org/property/colourname"}, "p2": {"type": "uri", "value": "http://wikidata.dbpedia.org/property/wiktionaryTitre"}}, {"p1": {"type": "uri", "value": "http://wikidata.dbpedia.org/property/colourname"}, "p2": {"type": "uri", "value": "http://wikidata.dbpedia.org/property/tekstkleur"}}, {"p1": {"type": "uri", "value": "http://wikidata.dbpedia.org/property/colourname"}, "p2": {"type": "uri", "value": "http://wikidata.dbpedia.org/property/h"}}, {"p1": {"type": "uri", "value": "http://wikidata.dbpedia.org/property/colourname"}, "p2": {"type": "uri", "value": "http://wikidata.dbpedia.org/property/k"}}, {"p1": {"type": "uri", "value": "http://wikidata.dbpedia.org/property/colourname"}, "p2": {"type": "uri", "value": "http://wikidata.dbpedia.org/property/nom"}}, {"p1": {"type": "uri", "value": "http://wikidata.dbpedia.org/property/colourname"}, "p2": {"type": "uri", "value": "http://wikidata.dbpedia.org/property/r"}}, {"p1": {"type": "uri", "value": "http://wikidata.dbpedia.org/property/colourname"}, "p2": {"type": "uri", "value": "http://wikidata.dbpedia.org/property/imagenPie"}}, {"p1": {"type": "uri", "value": "http://wikidata.dbpedia.org/property/colourname"}, "p2": {"type": "uri", "value": "http://wikidata.dbpedia.org/property/comprimento"}}, {"p1": {"type": "uri", "value": "http://wikidata.dbpedia.org/property/colourname"}, "p2": {"type": "uri", "value": "http://wikidata.dbpedia.org/property/pr\u00e9nom"}}, {"p1": {"type": "uri", "value": "http://wikidata.dbpedia.org/property/colourname"}, "p2": {"type": "uri", "value": "http://wikidata.dbpedia.org/property/imagem"}}, {"p1": {"type": "uri", "value": "http://wikidata.dbpedia.org/property/colourname"}, "p2": {"type": "uri", "value": "http://wikidata.dbpedia.org/property/sousTitre"}}, {"p1": {"type": "uri", "value": "http://wikidata.dbpedia.org/property/colourname"}, "p2": {"type": "uri", "value": "http://wikidata.dbpedia.org/property/ann\u00e9ePremi\u00e8re\u00c9dition"}}, {"p1": {"type": "uri", "value": "http://wikidata.dbpedia.org/property/colourname"}, "p2": {"type": "uri", "value": "http://wikidata.dbpedia.org/property/munsell"}}, {"p1": {"type": "uri", "value": "http://wikidata.dbpedia.org/property/colourname"}, "p2": {"type": "uri", "value": "http://wikidata.dbpedia.org/property/titre"}}, {"p1": {"type": "uri", "value": "http://wikidata.dbpedia.org/property/colourname"}, "p2": {"type": "uri", "value": "http://wikidata.dbpedia.org/property/spelling"}}, {"p1": {"type": "uri", "value": "http://wikidata.dbpedia.org/property/colourname"}, "p2": {"type": "uri", "value": "http://wikidata.dbpedia.org/property/textcolor"}}, {"p1": {"type": "uri", "value": "http://wikidata.dbpedia.org/property/colourname"}, "p2": {"type": "uri", "value": "http://wikidata.dbpedia.org/property/trad"}}, {"p1": {"type": "uri", "value": "http://wikidata.dbpedia.org/property/colourname"}, "p2": {"type": "uri", "value": "http://wikidata.dbpedia.org/property/fr"}}, {"p1": {"type": "uri", "value": "http://wikidata.dbpedia.org/property/colourname"}, "p2": {"type": "uri", "value": "http://wikidata.dbpedia.org/property/m"}}, {"p1": {"type": "uri", "value": "http://wikidata.dbpedia.org/property/colourname"}, "p2": {"type": "uri", "value": "http://wikidata.dbpedia.org/property/isbn"}}, {"p1": {"type": "uri", "value": "http://wikidata.dbpedia.org/property/colourname"}, "p2": {"type": "uri", "value": "http://wikidata.dbpedia.org/property/english"}}, {"p1": {"type": "uri", "value": "http://wikidata.dbpedia.org/property/colourname"}, "p2": {"type": "uri", "value": "http://wikidata.dbpedia.org/property/nome"}}, {"p1": {"type": "uri", "value": "http://wikidata.dbpedia.org/property/colourname"}, "p2": {"type": "uri", "value": "http://wikidata.dbpedia.org/property/pr\u00e9face"}}, {"p1": {"type": "uri", "value": "http://wikidata.dbpedia.org/property/colourname"}, "p2": {"type": "uri", "value": "http://wikidata.dbpedia.org/property/cor"}}, {"p1": {"type": "uri", "value": "http://wikidata.dbpedia.org/property/colourname"}, "p2": {"type": "uri", "value": "http://wikidata.dbpedia.org/property/\u043f\u043e\u0440\u0442\u0430\u043b"}}, {"p1": {"type": "uri", "value": "http://wikidata.dbpedia.org/property/colourname"}, "p2": {"type": "uri", "value": "http://wikidata.dbpedia.org/property/\u0442\u0435\u043c\u0430"}}, {"p1": {"type": "uri", "value": "http://wikidata.dbpedia.org/property/colourname"}, "p2": {"type": "uri", "value": "http://wikidata.dbpedia.org/property/wavelength"}}, {"p1": {"type": "uri", "value": "http://wikidata.dbpedia.org/property/colourname"}, "p2": {"type": "uri", "value": "http://wikidata.dbpedia.org/property/kana"}}, {"p1": {"type": "uri", "value": "http://wikidata.dbpedia.org/property/colourname"}, "p2": {"type": "uri", "value": "http://wikidata.dbpedia.org/property/\u00e9diteur"}}, {"p1": {"type": "uri", "value": "http://wikidata.dbpedia.org/property/colourname"}, "p2": {"type": "uri", "value": "http://purl.org/dc/elements/1.1/publisher"}}, {"p1": {"type": "uri", "value": "http://wikidata.dbpedia.org/property/colourname"}, "p2": {"type": "uri", "value": "http://dbpedia.org/ontology/individualisedGnd"}}, {"p1": {"type": "uri", "value": "http://wikidata.dbpedia.org/property/colourname"}, "p2": {"type": "uri", "value": "http://dbpedia.org/ontology/name"}}, {"p1": {"type": "uri", "value": "http://wikidata.dbpedia.org/property/colourname"}, "p2": {"type": "uri", "value": "http://dbpedia.org/ontology/originalTitle"}}, {"p1": {"type": "uri", "value": "http://wikidata.dbpedia.org/property/colourname"}, "p2": {"type": "uri", "value": "http://xmlns.com/foaf/0.1/name"}}, {"p1": {"type": "uri", "value": "http://wikidata.dbpedia.org/property/colourname"}, "p2": {"type": "uri", "value": "http://dbpedia.org/ontology/colourHexCode"}}, {"p1": {"type": "uri", "value": "http://wikidata.dbpedia.org/property/colourname"}, "p2": {"type": "uri", "value": "http://dbpedia.org/ontology/abstract"}}, {"p1": {"type": "uri", "value": "http://wikidata.dbpedia.org/property/colourname"}, "p2": {"type": "uri", "value": "http://wikidata.dbpedia.org/ontology/wavelength"}}, {"p1": {"type": "uri", "value": "http://wikidata.dbpedia.org/property/colourname"}, "p2": {"type": "uri", "value": "http://wikidata.dbpedia.org/ontology/abstract"}}, {"p1": {"type": "uri", "value": "http://wikidata.dbpedia.org/property/colourname"}, "p2": {"type": "uri", "value": "http://dbpedia.org/ontology/cmykCoordinateBlack"}}, {"p1": {"type": "uri", "value": "http://wikidata.dbpedia.org/property/colourname"}, "p2": {"type": "uri", "value": "http://dbpedia.org/ontology/cmykCoordinateCyanic"}}, {"p1": {"type": "uri", "value": "http://wikidata.dbpedia.org/property/colourname"}, "p2": {"type": "uri", "value": "http://dbpedia.org/ontology/cmykCoordinateMagenta"}}, {"p1": {"type": "uri", "value": "http://wikidata.dbpedia.org/property/colourname"}, "p2": {"type": "uri", "value": "http://dbpedia.org/ontology/cmykCoordinateYellow"}}, {"p1": {"type": "uri", "value": "http://wikidata.dbpedia.org/property/colourname"}, "p2": {"type": "uri", "value": "http://dbpedia.org/ontology/hsvCoordinateHue"}}, {"p1": {"type": "uri", "value": "http://wikidata.dbpedia.org/property/colourname"}, "p2": {"type": "uri", "value": "http://dbpedia.org/ontology/hsvCoordinateSaturation"}}, {"p1": {"type": "uri", "value": "http://wikidata.dbpedia.org/property/colourname"}, "p2": {"type": "uri", "value": "http://dbpedia.org/ontology/hsvCoordinateValue"}}, {"p1": {"type": "uri", "value": "http://wikidata.dbpedia.org/property/colourname"}, "p2": {"type": "uri", "value": "http://dbpedia.org/ontology/rgbCoordinateBlue"}}, {"p1": {"type": "uri", "value": "http://wikidata.dbpedia.org/property/colourname"}, "p2": {"type": "uri", "value": "http://dbpedia.org/ontology/rgbCoordinateGreen"}}, {"p1": {"type": "uri", "value": "http://wikidata.dbpedia.org/property/colourname"}, "p2": {"type": "uri", "value": "http://dbpedia.org/ontology/rgbCoordinateRed"}}, {"p1": {"type": "uri", "value": "http://wikidata.dbpedia.org/property/colourname"}, "p2": {"type": "uri", "value": "http://wikidata.dbpedia.org/ontology/colourHexCode"}}, {"p1": {"type": "uri", "value": "http://wikidata.dbpedia.org/property/colourname"}, "p2": {"type": "uri", "value": "http://wikidata.dbpedia.org/ontology/frequency"}}, {"p1": {"type": "uri", "value": "http://wikidata.dbpedia.org/property/colourname"}, "p2": {"type": "uri", "value": "http://wikidata.dbpedia.org/ontology/hsvCoordinateHue"}}, {"p1": {"type": "uri", "value": "http://wikidata.dbpedia.org/property/colourname"}, "p2": {"type": "uri", "value": "http://wikidata.dbpedia.org/ontology/hsvCoordinateSaturation"}}, {"p1": {"type": "uri", "value": "http://wikidata.dbpedia.org/property/colourname"}, "p2": {"type": "uri", "value": "http://wikidata.dbpedia.org/ontology/hsvCoordinateValue"}}, {"p1": {"type": "uri", "value": "http://wikidata.dbpedia.org/property/colourname"}, "p2": {"type": "uri", "value": "http://wikidata.dbpedia.org/ontology/rgbCoordinateBlue"}}, {"p1": {"type": "uri", "value": "http://wikidata.dbpedia.org/property/colourname"}, "p2": {"type": "uri", "value": "http://wikidata.dbpedia.org/ontology/rgbCoordinateGreen"}}, {"p1": {"type": "uri", "value": "http://wikidata.dbpedia.org/property/colourname"}, "p2": {"type": "uri", "value": "http://wikidata.dbpedia.org/ontology/rgbCoordinateRed"}}, {"p1": {"type": "uri", "value": "http://wikidata.dbpedia.org/property/colourname"}, "p2": {"type": "uri", "value": "http://dbpedia.org/ontology/wikiPageWikiLink"}}, {"p1": {"type": "uri", "value": "http://wikidata.dbpedia.org/property/colourname"}, "p2": {"type": "uri", "value": "http://wikidata.dbpedia.org/ontology/wikiPageWikiLink"}}]}}