{"head": {"link": [], "vars": ["e", "entities"]}, "results": {"distinct": false, "ordered": true, "bindings": [{"e": {"type": "uri", "value": "http://dbpedia.org/resource/The_Young_and_The_Brave"}, "entities": {"type": "typed-literal", "datatype": "http://www.w3.org/2001/XMLSchema#integer", "value": "55"}}, {"e": {"type": "uri", "value": "http://dbpedia.org/resource/20_Dates"}, "entities": {"type": "typed-literal", "datatype": "http://www.w3.org/2001/XMLSchema#integer", "value": "54"}}, {"e": {"type": "uri", "value": "http://dbpedia.org/resource/Taxi_dance_hall"}, "entities": {"type": "typed-literal", "datatype": "http://www.w3.org/2001/XMLSchema#integer", "value": "49"}}, {"e": {"type": "uri", "value": "http://dbpedia.org/resource/Kontinental_Hockey_League"}, "entities": {"type": "typed-literal", "datatype": "http://www.w3.org/2001/XMLSchema#integer", "value": "4836"}}, {"e": {"type": "uri", "value": "http://dbpedia.org/resource/Luigi_Cocilovo"}, "entities": {"type": "typed-literal", "datatype": "http://www.w3.org/2001/XMLSchema#integer", "value": "26"}}, {"e": {"type": "uri", "value": "http://dbpedia.org/resource/NCSU"}, "entities": {"type": "typed-literal", "datatype": "http://www.w3.org/2001/XMLSchema#integer", "value": "24"}}, {"e": {"type": "uri", "value": "http://dbpedia.org/resource/Belfast_South_(Northern_Ireland_Parliament_constituency)"}, "entities": {"type": "typed-literal", "datatype": "http://www.w3.org/2001/XMLSchema#integer", "value": "47"}}, {"e": {"type": "uri", "value": "http://dbpedia.org/resource/Diver"}, "entities": {"type": "typed-literal", "datatype": "http://www.w3.org/2001/XMLSchema#integer", "value": "29"}}, {"e": {"type": "uri", "value": "http://dbpedia.org/resource/Category:Television_stations_in_Lebanon"}, "entities": {"type": "typed-literal", "datatype": "http://www.w3.org/2001/XMLSchema#integer", "value": "19"}}, {"e": {"type": "uri", "value": "http://dbpedia.org/resource/Lower_Normandy"}, "entities": {"type": "typed-literal", "datatype": "http://www.w3.org/2001/XMLSchema#integer", "value": "378"}}, {"e": {"type": "uri", "value": "http://dbpedia.org/resource/The_Family_Way"}, "entities": {"type": "typed-literal", "datatype": "http://www.w3.org/2001/XMLSchema#integer", "value": "122"}}, {"e": {"type": "uri", "value": "http://dbpedia.org/resource/Barthold_A._Butensch%C3%B8n,_Sr."}, "entities": {"type": "typed-literal", "datatype": "http://www.w3.org/2001/XMLSchema#integer", "value": "1"}}, {"e": {"type": "uri", "value": "http://dbpedia.org/resource/EC-Council"}, "entities": {"type": "typed-literal", "datatype": "http://www.w3.org/2001/XMLSchema#integer", "value": "42"}}, {"e": {"type": "uri", "value": "http://dbpedia.org/resource/1977_Air_Canada_Silver_Broom"}, "entities": {"type": "typed-literal", "datatype": "http://www.w3.org/2001/XMLSchema#integer", "value": "44"}}, {"e": {"type": "uri", "value": "http://de.dbpedia.org/resource/Constantine_(Fernsehserie)"}, "entities": {"type": "typed-literal", "datatype": "http://www.w3.org/2001/XMLSchema#integer", "value": "72"}}, {"e": {"type": "uri", "value": "http://dbpedia.org/resource/Twin_Cinema"}, "entities": {"type": "typed-literal", "datatype": "http://www.w3.org/2001/XMLSchema#integer", "value": "96"}}, {"e": {"type": "uri", "value": "http://dbpedia.org/resource/Baryogenesis"}, "entities": {"type": "typed-literal", "datatype": "http://www.w3.org/2001/XMLSchema#integer", "value": "136"}}, {"e": {"type": "uri", "value": "http://dbpedia.org/resource/Demographic_history_of_Pomerania"}, "entities": {"type": "typed-literal", "datatype": "http://www.w3.org/2001/XMLSchema#integer", "value": "19"}}, {"e": {"type": "uri", "value": "http://dbpedia.org/resource/Category:History_of_County_Durham"}, "entities": {"type": "typed-literal", "datatype": "http://www.w3.org/2001/XMLSchema#integer", "value": "10"}}, {"e": {"type": "uri", "value": "http://dbpedia.org/resource/Donald_Bradman"}, "entities": {"type": "typed-literal", "datatype": "http://www.w3.org/2001/XMLSchema#integer", "value": "376"}}, {"e": {"type": "uri", "value": "http://dbpedia.org/resource/Troller's_Gill"}, "entities": {"type": "typed-literal", "datatype": "http://www.w3.org/2001/XMLSchema#integer", "value": "32"}}, {"e": {"type": "uri", "value": "http://dbpedia.org/resource/Ratlam"}, "entities": {"type": "typed-literal", "datatype": "http://www.w3.org/2001/XMLSchema#integer", "value": "261"}}, {"e": {"type": "uri", "value": "http://dbpedia.org/resource/Lex_Luthor"}, "entities": {"type": "typed-literal", "datatype": "http://www.w3.org/2001/XMLSchema#integer", "value": "1302"}}, {"e": {"type": "uri", "value": "http://dbpedia.org/resource/Where_Are_My_Children%3F"}, "entities": {"type": "typed-literal", "datatype": "http://www.w3.org/2001/XMLSchema#integer", "value": "53"}}, {"e": {"type": "uri", "value": "http://dbpedia.org/resource/Embassy_of_Kyrgyzstan,_London"}, "entities": {"type": "typed-literal", "datatype": "http://www.w3.org/2001/XMLSchema#integer", "value": "18"}}, {"e": {"type": "uri", "value": "http://dbpedia.org/resource/Glory_to_the_Filmmaker!"}, "entities": {"type": "typed-literal", "datatype": "http://www.w3.org/2001/XMLSchema#integer", "value": "78"}}, {"e": {"type": "uri", "value": "http://dbpedia.org/resource/Dino_Entertainment"}, "entities": {"type": "typed-literal", "datatype": "http://www.w3.org/2001/XMLSchema#integer", "value": "31"}}, {"e": {"type": "uri", "value": "http://dbpedia.org/resource/Economics"}, "entities": {"type": "typed-literal", "datatype": "http://www.w3.org/2001/XMLSchema#integer", "value": "9253"}}, {"e": {"type": "uri", "value": "http://dbpedia.org/resource/Self-information"}, "entities": {"type": "typed-literal", "datatype": "http://www.w3.org/2001/XMLSchema#integer", "value": "67"}}, {"e": {"type": "uri", "value": "http://dbpedia.org/resource/This_Is_England"}, "entities": {"type": "typed-literal", "datatype": "http://www.w3.org/2001/XMLSchema#integer", "value": "217"}}, {"e": {"type": "uri", "value": "http://dbpedia.org/resource/Abingdon,_Illinois"}, "entities": {"type": "typed-literal", "datatype": "http://www.w3.org/2001/XMLSchema#integer", "value": "117"}}, {"e": {"type": "uri", "value": "http://dbpedia.org/resource/Francisco_Hern%C3%A1ndez_Marcos"}, "entities": {"type": "typed-literal", "datatype": "http://www.w3.org/2001/XMLSchema#integer", "value": "1"}}, {"e": {"type": "uri", "value": "http://dbpedia.org/resource/Wood_car_racing"}, "entities": {"type": "typed-literal", "datatype": "http://www.w3.org/2001/XMLSchema#integer", "value": "33"}}, {"e": {"type": "uri", "value": "http://dbpedia.org/resource/The_Desert's_Toll"}, "entities": {"type": "typed-literal", "datatype": "http://www.w3.org/2001/XMLSchema#integer", "value": "33"}}, {"e": {"type": "uri", "value": "http://dbpedia.org/resource/Gary_Anderson"}, "entities": {"type": "typed-literal", "datatype": "http://www.w3.org/2001/XMLSchema#integer", "value": "25"}}, {"e": {"type": "uri", "value": "http://dbpedia.org/resource/The_Ghost_House_(film)"}, "entities": {"type": "typed-literal", "datatype": "http://www.w3.org/2001/XMLSchema#integer", "value": "45"}}, {"e": {"type": "uri", "value": "http://dbpedia.org/resource/Habermann_(film)"}, "entities": {"type": "typed-literal", "datatype": "http://www.w3.org/2001/XMLSchema#integer", "value": "44"}}, {"e": {"type": "uri", "value": "http://dbpedia.org/resource/Nordicity"}, "entities": {"type": "typed-literal", "datatype": "http://www.w3.org/2001/XMLSchema#integer", "value": "33"}}, {"e": {"type": "uri", "value": "http://dbpedia.org/resource/Swimsuit"}, "entities": {"type": "typed-literal", "datatype": "http://www.w3.org/2001/XMLSchema#integer", "value": "345"}}, {"e": {"type": "uri", "value": "http://dbpedia.org/resource/Anti-art"}, "entities": {"type": "typed-literal", "datatype": "http://www.w3.org/2001/XMLSchema#integer", "value": "162"}}, {"e": {"type": "uri", "value": "http://dbpedia.org/resource/Isle_of_Man"}, "entities": {"type": "typed-literal", "datatype": "http://www.w3.org/2001/XMLSchema#integer", "value": "4977"}}, {"e": {"type": "uri", "value": "http://dbpedia.org/resource/Developed_country"}, "entities": {"type": "typed-literal", "datatype": "http://www.w3.org/2001/XMLSchema#integer", "value": "672"}}, {"e": {"type": "uri", "value": "http://dbpedia.org/resource/Arshad_Warsi"}, "entities": {"type": "typed-literal", "datatype": "http://www.w3.org/2001/XMLSchema#integer", "value": "473"}}]}}